ai_supporter/__init__.py
ai_supporter/tts.py
ai_supporter/tts_old.py
ai_supporter-0.0.3.dist-info/METADATA
ai_supporter-0.0.3.dist-info/WHEEL
ai_supporter-0.0.3.dist-info/top_level.txt
ai_supporter-0.0.3.dist-info/RECORD
