Metadata-Version: 2.1
Name: ai-supporter
Version: 0.0.3
Summary: Ai supporter
Home-page: https://github.com/automatethem/ai-supporter
Author: Sang Ki Kwon
Author-email: automatethem@gmail.com
License: MIT
Requires-Dist: gtts
Requires-Dist: pygame
